goodgit/__init__.py
goodgit/__main__.py
goodgit/analytics.py
goodgit/goodgit.py
goodgit/tests.py
goodgit/branch/__init__.py
goodgit/branch/__main__.py
goodgit/branch/branch.py
goodgit/commit/__init__.py
goodgit/commit/__main__.py
goodgit/commit/add.py
goodgit/commit/commit.py
goodgit/commit/init.py
goodgit/commit/push.py
goodgit/commit/uncommit.py
goodgit/github/__init__.py
goodgit/github/__main__.py
goodgit/github/github.py
goodgit/merge/__init__.py
goodgit/merge/__main__.py
goodgit/merge/merge.py
goodgit/merge/pull.py
goodgit/publish/__init__.py
goodgit/publish/__main__.py
goodgit/publish/clone.py
goodgit/publish/publish.py
goodgit/search/__init__.py
goodgit/search/__main__.py
goodgit/search/search.py
goodgit/ssh/__init__.py
goodgit/ssh/__main__.py
goodgit/ssh/ssh.py
goodgit/timetravel/__init__.py
goodgit/timetravel/__main__.py
goodgit/timetravel/apply.py
goodgit/timetravel/timetravel.py
goodgit/utils/__init__.py
goodgit/utils/__main__.py
goodgit/utils/utils.py
goodgit/web/__init__.py
goodgit/web/__main__.py
goodgit/web/web.py
goodgit-0.1.32.dist-info/LICENCE
goodgit-0.1.32.dist-info/METADATA
goodgit-0.1.32.dist-info/WHEEL
goodgit-0.1.32.dist-info/entry_points.txt
goodgit-0.1.32.dist-info/top_level.txt
goodgit-0.1.32.dist-info/RECORD
