Metadata-Version: 2.1
Name: goodgit
Version: 0.1.32
Summary: Git; for humans
Author: Shubham Gupta • Saket Gupta
Author-email: shubhastro2@gmail.com
License-File: LICENCE
Requires-Dist: GitPython
Requires-Dist: docopt
Requires-Dist: halo
Requires-Dist: questionary
Requires-Dist: remote-log
Requires-Dist: requests
Requires-Dist: rich
